setup.py
chiru150.egg-info/PKG-INFO
chiru150.egg-info/SOURCES.txt
chiru150.egg-info/dependency_links.txt
chiru150.egg-info/top_level.txt
gpsk/__init__.py
gpsk/palindromee.py