Metadata-Version: 1.0
Name: chiru150
Version: 0.1.1
Summary: Useful towel-related stuff.
Home-page: http://pypi.python.org/pypi/MyApplication_v010/
Author: name surname
Author-email: name@addr.ess
License: UNKNOWN
Platform: UNKNOWN
